{
  "achievements_v5": {
    "first_flight": {
      "id": "first_flight",
      "name": "Первый полёт",
      "description": "Завершите главу 1 и получите свой первый корабль",
      "icon": "🚀",
      "category": "story",
      "points": 50,
      "hidden": false,
      "requirement": {"type": "chapter_complete", "chapter": 1}
    },
    "echo_contact": {
      "id": "echo_contact",
      "name": "Голос из глубины",
      "description": "Установите контакт с Эхом в главе 11",
      "icon": "🔮",
      "category": "story",
      "points": 40,
      "hidden": false,
      "requirement": {"type": "dialogue_complete", "dialogue_id": "echo_first_contact"}
    },
    "path_chosen": {
      "id": "path_chosen",
      "name": "Выбор сделан",
      "description": "Выберите свой путь в главе 13",
      "icon": "⛤",
      "category": "story",
      "points": 75,
      "hidden": false,
      "requirement": {"type": "event", "event_id": "path_selected"}
    },
    "survivor_found": {
      "id": "survivor_found",
      "name": "След выжившего",
      "description": "Найдите информацию о выжившем из Зоны Тишины",
      "icon": "👣",
      "category": "exploration",
      "points": 35,
      "hidden": false,
      "requirement": {"type": "quest_complete", "quest_id": "q11_02"}
    },
    "crystal_obtained": {
      "id": "crystal_obtained",
      "name": "Кристалл Времени",
      "description": "Получите Кристалл Времени из древнего храма",
      "icon": "💎",
      "category": "story",
      "points": 60,
      "hidden": false,
      "requirement": {"type": "item_obtained", "item_id": "time_crystal"}
    },
    "traitor_revealed": {
      "id": "traitor_revealed",
      "name": "Лицо врага",
      "description": "Раскройте предателя в главе 15",
      "icon": "🎭",
      "category": "story",
      "points": 80,
      "hidden": true,
      "requirement": {"type": "event", "event_id": "traitor_confronted"}
    },
    "zone_silence_entered": {
      "id": "zone_silence_entered",
      "name": "Зона Тишины",
      "description": "Войдите в Зону Тишины и выживите",
      "icon": "🌑",
      "category": "exploration",
      "points": 50,
      "hidden": false,
      "requirement": {"type": "location_visited", "location_id": "zone_silence"}
    },
    "guardian_met": {
      "id": "guardian_met",
      "name": "Древний Страж",
      "description": "Встретьтесь со Стражем Ядра",
      "icon": "🗿",
      "category": "story",
      "points": 70,
      "hidden": false,
      "requirement": {"type": "dialogue_complete", "dialogue_id": "guardian_encounter"}
    },

    "exile_hero": {
      "id": "exile_hero",
      "name": "Изгнание Тьмы",
      "description": "Завершите игру финалом Изгнания",
      "icon": "☀️",
      "category": "ending",
      "points": 200,
      "hidden": false,
      "requirement": {"type": "ending", "ending_id": "exile"}
    },
    "treaty_keeper": {
      "id": "treaty_keeper",
      "name": "Хранитель Границы",
      "description": "Завершите игру финалом Договора",
      "icon": "⚖️",
      "category": "ending",
      "points": 200,
      "hidden": false,
      "requirement": {"type": "ending", "ending_id": "treaty"}
    },
    "transcendent": {
      "id": "transcendent",
      "name": "Трансценденция",
      "description": "Завершите игру финалом Слияния",
      "icon": "♾️",
      "category": "ending",
      "points": 300,
      "hidden": true,
      "requirement": {"type": "ending", "ending_id": "merge"}
    },
    "all_endings": {
      "id": "all_endings",
      "name": "Мастер судеб",
      "description": "Получите все три концовки",
      "icon": "🔱",
      "category": "ending",
      "points": 500,
      "hidden": true,
      "requirement": {"type": "endings_count", "count": 3}
    },

    "first_kiss": {
      "id": "first_kiss",
      "name": "Первый поцелуй",
      "description": "Начните романтические отношения с персонажем",
      "icon": "💕",
      "category": "romance",
      "points": 30,
      "hidden": false,
      "requirement": {"type": "romance_level", "level": 50}
    },
    "true_love_mia": {
      "id": "true_love_mia",
      "name": "Тактический союз",
      "description": "Достигните максимальных отношений с Мией",
      "icon": "❤️",
      "category": "romance",
      "points": 100,
      "hidden": false,
      "requirement": {"type": "character_relationship", "character": "mia", "value": 100}
    },
    "true_love_maria": {
      "id": "true_love_maria",
      "name": "Исцеление сердца",
      "description": "Достигните максимальных отношений с Марией",
      "icon": "❤️",
      "category": "romance",
      "points": 100,
      "hidden": false,
      "requirement": {"type": "character_relationship", "character": "maria", "value": 100}
    },
    "true_love_anna": {
      "id": "true_love_anna",
      "name": "Звёздный навигатор",
      "description": "Достигните максимальных отношений с Анной",
      "icon": "❤️",
      "category": "romance",
      "points": 100,
      "hidden": false,
      "requirement": {"type": "character_relationship", "character": "anna", "value": 100}
    },
    "true_love_veronica": {
      "id": "true_love_veronica",
      "name": "Теневой альянс",
      "description": "Достигните максимальных отношений с Вероникой",
      "icon": "❤️",
      "category": "romance",
      "points": 100,
      "hidden": false,
      "requirement": {"type": "character_relationship", "character": "veronica", "value": 100}
    },
    "true_love_zara": {
      "id": "true_love_zara",
      "name": "Рыцарь и мистик",
      "description": "Достигните максимальных отношений с Зарой",
      "icon": "❤️",
      "category": "romance",
      "points": 100,
      "hidden": false,
      "requirement": {"type": "character_relationship", "character": "zara", "value": 100}
    },
    "true_love_athena": {
      "id": "true_love_athena",
      "name": "Цифровая любовь",
      "description": "Достигните максимальных отношений с Афиной",
      "icon": "❤️",
      "category": "romance",
      "points": 150,
      "hidden": true,
      "requirement": {"type": "character_relationship", "character": "athena", "value": 100}
    },
    "true_love_alia": {
      "id": "true_love_alia",
      "name": "Биотическая связь",
      "description": "Достигните максимальных отношений с Алиёй",
      "icon": "❤️",
      "category": "romance",
      "points": 150,
      "hidden": false,
      "requirement": {"type": "character_relationship", "character": "alia_naar", "value": 100}
    },
    "heartbreaker": {
      "id": "heartbreaker",
      "name": "Разбиватель сердец",
      "description": "Отвергните 3 романтических предложения",
      "icon": "💔",
      "category": "romance",
      "points": 50,
      "hidden": true,
      "requirement": {"type": "romance_rejections", "count": 3}
    },
    "polyamory_master": {
      "id": "polyamory_master",
      "name": "Мастер полиамории",
      "description": "Поддерживайте отношения с 3 партнёрами одновременно",
      "icon": "💞",
      "category": "romance",
      "points": 200,
      "hidden": true,
      "requirement": {"type": "simultaneous_relationships", "count": 3}
    },

    "resonance_level_2": {
      "id": "resonance_level_2",
      "name": "Пробуждение Резонанса",
      "description": "Достигните 2 уровня Резонанса",
      "icon": "✨",
      "category": "mechanics",
      "points": 40,
      "hidden": false,
      "requirement": {"type": "resonance_level", "level": 2}
    },
    "resonance_level_3": {
      "id": "resonance_level_3",
      "name": "Мастер Резонанса",
      "description": "Достигните 3 уровня Резонанса",
      "icon": "🌟",
      "category": "mechanics",
      "points": 75,
      "hidden": false,
      "requirement": {"type": "resonance_level", "level": 3}
    },
    "resonance_level_4": {
      "id": "resonance_level_4",
      "name": "Трансцендентный",
      "description": "Достигните максимального уровня Резонанса",
      "icon": "⭐",
      "category": "mechanics",
      "points": 150,
      "hidden": true,
      "requirement": {"type": "resonance_level", "level": 4}
    },

    "diplomatic_victory": {
      "id": "diplomatic_victory",
      "name": "Дипломатическая победа",
      "description": "Решите 10 конфликтов мирным путём",
      "icon": "🕊️",
      "category": "gameplay",
      "points": 60,
      "hidden": false,
      "requirement": {"type": "peaceful_resolutions", "count": 10}
    },
    "tactical_genius": {
      "id": "tactical_genius",
      "name": "Тактический гений",
      "description": "Выиграйте 10 боёв без потерь",
      "icon": "🎯",
      "category": "combat",
      "points": 80,
      "hidden": false,
      "requirement": {"type": "flawless_victories", "count": 10}
    },
    "survivor": {
      "id": "survivor",
      "name": "Выживший",
      "description": "Выживите после 5 критических ситуаций",
      "icon": "🛡️",
      "category": "survival",
      "points": 50,
      "hidden": false,
      "requirement": {"type": "critical_survivals", "count": 5}
    },
    "treasure_hunter": {
      "id": "treasure_hunter",
      "name": "Охотник за сокровищами",
      "description": "Найдите 20 скрытых артефактов",
      "icon": "💰",
      "category": "exploration",
      "points": 70,
      "hidden": false,
      "requirement": {"type": "artifacts_found", "count": 20}
    },
    "completionist": {
      "id": "completionist",
      "name": "Коллекционер",
      "description": "Соберите все достижения",
      "icon": "🏆",
      "category": "meta",
      "points": 1000,
      "hidden": true,
      "requirement": {"type": "all_achievements"}
    }
  }
}
